<?xml version="1.0" ?>
<!DOCTYPE PISI SYSTEM "http://www.pardus.org.tr/projeler/pisi/pisi-spec.dtd">
<PISI>
    <Source>
        <Name>clisp</Name>
        <Homepage>http://clisp.cons.org/</Homepage>
        <Packager>
            <Name>Çağlar Kilimci</Name>
            <Email>ckilimci@pardus.org.tr</Email>
        </Packager>
        <License>GPLv2</License>
        <IsA>app:console</IsA>
        <Summary>An ANSI Common Lisp Implementation</Summary>
        <Description>ANSI Common Lisp is a high-level, general-purpose programming language.</Description>
        <Archive sha1sum="7e8d585ef8d0d6349ffe581d1ac08681e6e670d4" type="tarbz2">mirrors://sourceforge/clisp/clisp-2.49.tar.bz2</Archive>
        <BuildDependencies>
            <Dependency>libsigsegv</Dependency>
            <Dependency>ffcall-devel</Dependency>
            <Dependency>libglade-devel</Dependency>
            <Dependency>fcgi-devel</Dependency>
            <Dependency versionFrom="2.18.5">gtk2-devel</Dependency>
            <Dependency>postgresql-lib</Dependency>
            <Dependency>pcre++-devel</Dependency>
            <Dependency>pari</Dependency>
            <Dependency>libSM-devel</Dependency>
            <Dependency>libXaw-devel</Dependency>
            <Dependency>libXft-devel</Dependency>
            <Dependency>libXmu-devel</Dependency>
            <Dependency>libXrender-devel</Dependency>
            <Dependency>libXt-devel</Dependency>
            <Dependency>libXpm-devel</Dependency>
            <Dependency>libXext-devel</Dependency>
            <Dependency>gdk-pixbuf-devel</Dependency>
        </BuildDependencies>
        <Patches>
            <Patch level="1">clisp-link.in</Patch>
            <Patch level="1">init.lisp</Patch>
        </Patches>
    </Source>

    <Package>
        <Name>clisp</Name>
        <RuntimeDependencies>
            <Dependency>libsigsegv</Dependency>
            <Dependency>ffcall</Dependency>
            <Dependency>libglade</Dependency>
            <Dependency>fcgi</Dependency>
            <Dependency versionFrom="2.18.5">gtk2</Dependency>
            <Dependency>postgresql-lib</Dependency>
            <Dependency>pcre++</Dependency>
            <Dependency>pari</Dependency>
            <Dependency>libSM</Dependency>
            <Dependency>libXaw</Dependency>
            <Dependency>libXft</Dependency>
            <Dependency>libXmu</Dependency>
            <Dependency>libXrender</Dependency>
            <Dependency>libXt</Dependency>
            <Dependency>libXpm</Dependency>
            <Dependency>libXext</Dependency>
            <Dependency>gdk-pixbuf</Dependency>
        </RuntimeDependencies>
        <Files>
            <Path fileType="executable">/usr/bin</Path>
            <Path fileType="library">/usr/lib</Path>
            <Path fileType="data">/usr/share/vim</Path>
            <Path fileType="data">/usr/share/emacs</Path>
            <Path fileType="doc">/usr/share/doc</Path>
            <Path fileType="localedata">/usr/share/locale</Path>
            <Path fileType="man">/usr/share/man</Path>
        </Files>
    </Package>

    <Package>
        <Name>clisp-devel</Name>
        <Summary>Development files for clisp</Summary>
        <RuntimeDependencies>
            <Dependency release="current">clisp</Dependency>
        </RuntimeDependencies>
        <Files>
            <Path fileType="data">/usr/share/aclocal</Path>
        </Files>
    </Package>


    <History>
        <Update release="12">
            <Date>2010-12-30</Date>
            <Version>2.49</Version>
            <Comment>Build for 2011, new patches added, split devel package</Comment>
            <Name>Çağlar Kilimci</Name>
            <Email>ckilimci@pardus.org.tr</Email>
        </Update>
        <Update release="11">
            <Date>2010-12-21</Date>
            <Version>2.49</Version>
            <Comment>Version bump:
                * Function RENAME-FILE now accepts.
                * Module pcre 8.01 and previous versions now supports.
                * Module berkeley-db 4.8 and previous versions now supports.
                * Module postgresql 8.4 and previous versions now supports.
                Look for more information: http://clisp.cvs.sourceforge.net/viewvc/clisp/clisp/src/NEWS?revision=clisp_2_49-2010-07-07
            </Comment>
            <Name>Çağlar Kilimci</Name>
            <Email>ckilimci@pardus.org.tr</Email>
        </Update>
        <Update release="10">
            <Date>2009-08-15</Date>
            <Version>2.48</Version>
            <Comment>Version bump, many bugfixes and compile new modules.</Comment>
            <Name>İnanç Yıldırgan</Name>
            <Email>inancyildirgan@gmail.com</Email>
        </Update>
        <Update release="9">
            <Date>2009-05-27</Date>
            <Version>2.47</Version>
            <Comment>Set execute bit of clisp-link script, remove system.base dependencies.</Comment>
            <Name>H. İbrahim Güngör</Name>
            <Email>h.ibrahim.gungor@gmail.com</Email>
        </Update>
        <Update release="8">
            <Date>2009-04-26</Date>
            <Version>2.47</Version>
            <Comment>Remove tetex dep and emacs package.</Comment>
            <Name>İnanç Yıldırgan</Name>
            <Email>inancyildirgan@gmail.com</Email>
        </Update>
        <Update release="7">
            <Date>2008-11-27</Date>
            <Version>2.47</Version>
            <Comment>Add missing man file into the package (Fixes #8555).</Comment>
            <Name>Ozan Çağlayan</Name>
            <Email>ozan@pardus.org.tr</Email>
        </Update>
        <Update release="6">
            <Date>2008-10-24</Date>
            <Version>2.47</Version>
            <Comment>Stable update.</Comment>
            <Name>İnanç Yıldırgan</Name>
            <Email>inancyildirgan@gmail.com</Email>
        </Update>
        <Update release="5">
            <Date>2008-10-07</Date>
            <Version>2.46</Version>
            <Comment>Add missing deps, remove unneeded deps</Comment>
            <Name>Fatih Aşıcı</Name>
            <Email>fatih@pardus.org.tr</Email>
        </Update>
        <Update release="4">
            <Date>2008-09-18</Date>
            <Version>2.46</Version>
            <Comment>Version bump</Comment>
            <Name>İnanç Yıldırgan</Name>
            <Email>inancyildirgan@gmail.com</Email>
        </Update>
        <Update release="3">
            <Date>2008-03-05</Date>
            <Version>2.43.1</Version>
            <Comment>Stable update</Comment>
            <Name>İsmail Dönmez</Name>
            <Email>ismail@pardus.org.tr</Email>
        </Update>
        <Update release="2">
            <Date>2007-12-17</Date>
            <Version>2.43</Version>
            <Comment>Stable update</Comment>
            <Name>İsmail Dönmez</Name>
            <Email>ismail@pardus.org.tr</Email>
        </Update>
        <Update release="1">
            <Date>2006-03-02</Date>
            <Version>2.38</Version>
            <Comment>First release.</Comment>
            <Name>İsmail Dönmez</Name>
            <Email>ismail@pardus.org.tr</Email>
        </Update>
    </History>
</PISI>
